LICENSE
MANIFEST.in
README.md
VERSION
setup.py
src/sat_heuristic_validator/aggregate.py
src/sat_heuristic_validator/dataset.py
src/sat_heuristic_validator/satisfy.py
src/sat_heuristic_validator/struct.py
src/sat_heuristic_validator/validation.py
src/sat_heuristic_validator.egg-info/PKG-INFO
src/sat_heuristic_validator.egg-info/SOURCES.txt
src/sat_heuristic_validator.egg-info/dependency_links.txt
src/sat_heuristic_validator.egg-info/requires.txt
src/sat_heuristic_validator.egg-info/top_level.txt